example_package/__init__.py
example_package/xiaoxi_search.py
fanxiaoxi-1.0.3.dist-info/METADATA
fanxiaoxi-1.0.3.dist-info/WHEEL
fanxiaoxi-1.0.3.dist-info/top_level.txt
fanxiaoxi-1.0.3.dist-info/RECORD
