Metadata-Version: 2.1
Name: fanxiaoxi
Version: 1.0.3
Summary: This software is some simple search
Home-page: https://gitee.com/fan-xiaoxixi/fan-xiaoxis-operation.git
Author: fan
Author-email: 1014054577@qq.com
